[
  {
    "character_Name": "테스트캐릭터",
    "character_StatuArr": [
      10.0,
      0.0,
      0.0,
      0.0,
      0.0,
      0.0,
      0.0,
      0.0,
      0.0,
      0.0,
      0.0,
      0.0,
      0.0,
      0.0
    ],
    "ability_Info": "무능합니다",
    "thumbnail_image": "Sprites/Enemy 0",
    "variances": [
      {
        "characterStatus": 0,
        "variance": 5.0
      },
      {
        "characterStatus": 7,
        "variance": 3.0
      },
      {
        "characterStatus": 6,
        "variance": -5.0
      },
      {
        "characterStatus": 11,
        "variance": 50.0
      }
    ]
  },
  {
    "character_Name": "테스트캐릭터2",
    "character_StatuArr": [
      10.0,
      0.0,
      0.0,
      0.0,
      0.0,
      0.0,
      0.0,
      0.0,
      0.0,
      0.0,
      0.0,
      0.0,
      0.0,
      0.0
    ],
    "ability_Info": "무능123123",
    "thumbnail_image": "Sprites/Enemy 1",
    "variances": [
      {
        "characterStatus": 0,
        "variance": -5.0
      },
      {
        "characterStatus": 3,
        "variance": 25.0
      },
      {
        "characterStatus": 11,
        "variance": 30.0
      }
    ]
  }
]